dualitee/__init__.py
tests/__init__.py
tests/test_popen.py
tests/test_run.py
dualitee-0.0.0.dist-info/LICENSE
dualitee-0.0.0.dist-info/METADATA
dualitee-0.0.0.dist-info/WHEEL
dualitee-0.0.0.dist-info/top_level.txt
dualitee-0.0.0.dist-info/RECORD
