Metadata-Version: 2.1
Name: dualitee
Version: 0.0.0
Summary: Emit your output and process it too
Home-page: UNKNOWN
Author: JD Friedrikson
Author-email: jd@conn.cx
License: BSD 3-Clause License
Platform: UNKNOWN
Classifier: License :: OSI Approved :: BSD License
Classifier: Programming Language :: Python
Classifier: Programming Language :: Python :: 3
Classifier: Programming Language :: Python :: 3 :: Only
Classifier: Operating System :: POSIX :: Linux
Requires-Dist: piquipe
